t_co/__init__.py
t_co/main.py
t_co/shortener.py
get_twitter_shortened_url-0.0.2.dist-info/LICENSE
get_twitter_shortened_url-0.0.2.dist-info/METADATA
get_twitter_shortened_url-0.0.2.dist-info/WHEEL
get_twitter_shortened_url-0.0.2.dist-info/entry_points.txt
get_twitter_shortened_url-0.0.2.dist-info/top_level.txt
get_twitter_shortened_url-0.0.2.dist-info/RECORD
