Metadata-Version: 2.1
Name: get-twitter-shortened-url
Version: 0.0.2
Summary: Get shortened link from Twitter URL Shortener (t.co)
Home-page: https://github.com/eggplants/get-twitter-shortened-url
Author: eggplants
License: MIT
Platform: UNKNOWN
Classifier: Topic :: Software Development :: Libraries
Classifier: License :: OSI Approved :: MIT License
Classifier: Programming Language :: Python
Classifier: Programming Language :: Python :: 3
Classifier: Programming Language :: Python :: 3 :: Only
Requires-Python: >=3.5
Requires-Dist: tweepy
Requires-Dist: python-dotenv
Requires-Dist: url-normalize
